[{"prev_value": 0.035617987314860024, "name": "array.FancyIndexing.time_fancy", "change_rev": [11149, 11151], "idx": null, "last_rev": 12194, "last_value": 0.035825490951538086, "pretty_name": "array.FancyIndexing.time_fancy", "last_err": 0.000474633493454835}, {"prev_value": 0.06938236554463705, "name": "array.Rechunk.time_rechunk", "change_rev": [null, 9394], "idx": null, "last_rev": 12194, "last_value": 0.06217396259307861, "pretty_name": "array.Rechunk.time_rechunk", "last_err": 0.0010523652924898375}, {"prev_value": null, "name": "array.Rechunk.time_rechunk_meta", "change_rev": null, "idx": null, "last_rev": 12194, "last_value": 0.0074675338608878, "pretty_name": "array.Rechunk.time_rechunk_meta", "last_err": 0.0011881417618823523}, {"prev_value": 0.016606433050973073, "name": "array.Slicing.time_slice_int_head", "change_rev": [null, 11459], "idx": null, "last_rev": 12194, "last_value": 0.017432570457458496, "pretty_name": "array.Slicing.time_slice_int_head", "last_err": 0.0001767938174517329}, {"prev_value": null, "name": "array.Slicing.time_slice_int_tail", "change_rev": null, "idx": null, "last_rev": 12194, "last_value": 0.01681685447692871, "pretty_name": "array.Slicing.time_slice_int_tail", "last_err": 0.00047691797351579975}, {"prev_value": 0.03638831774393717, "name": "array.Slicing.time_slice_slice_head", "change_rev": [11460, 11476], "idx": null, "last_rev": 12194, "last_value": 0.03740286827087402, "pretty_name": "array.Slicing.time_slice_slice_head", "last_err": 0.00016258800975778222}, {"prev_value": 0.03637401262919108, "name": "array.Slicing.time_slice_slice_tail", "change_rev": [null, 11459], "idx": null, "last_rev": 12194, "last_value": 0.03733956813812256, "pretty_name": "array.Slicing.time_slice_slice_tail", "last_err": 0.00019790193136376088}, {"prev_value": 0.10021734237670898, "name": "array.TestSubs.time_subs", "change_rev": [10122, 10124], "idx": null, "last_rev": 12194, "last_value": 0.09898102283477783, "pretty_name": "array.TestSubs.time_subs", "last_err": 0.0006891899805801038}, {"prev_value": 0.0007489202679067419, "name": "array.Tokenize.time_tokenize_large", "change_rev": [10235, 10251], "idx": null, "last_rev": 12194, "last_value": 0.0008019971496918622, "pretty_name": "array.Tokenize.time_tokenize_large", "last_err": 7.551086195795211e-06}, {"prev_value": 0.1089400053024292, "name": "array_overlap.MapOverlap.time_map_overlap", "change_rev": [11197, 11201], "idx": 0, "last_rev": 12194, "last_value": 0.11004340648651123, "pretty_name": "array_overlap.MapOverlap.time_map_overlap((100, 100, 100), 'reflect')", "last_err": 0.000684376790551181}, {"prev_value": 0.10757708549499512, "name": "array_overlap.MapOverlap.time_map_overlap", "change_rev": [11201, 11203], "idx": 1, "last_rev": 12194, "last_value": 0.10907459259033203, "pretty_name": "array_overlap.MapOverlap.time_map_overlap((100, 100, 100), 'periodic')", "last_err": 0.0005959225116026523}, {"prev_value": 0.10885393619537354, "name": "array_overlap.MapOverlap.time_map_overlap", "change_rev": [10969, 10974], "idx": 2, "last_rev": 12194, "last_value": 0.10988998413085938, "pretty_name": "array_overlap.MapOverlap.time_map_overlap((100, 100, 100), 'nearest')", "last_err": 0.0006853103975080823}, {"prev_value": 0.0253276526927948, "name": "array_overlap.MapOverlap.time_map_overlap", "change_rev": [11197, 11201], "idx": 3, "last_rev": 12194, "last_value": 0.02602553367614746, "pretty_name": "array_overlap.MapOverlap.time_map_overlap((100, 100, 100), 'none')", "last_err": 0.0001795810535753617}, {"prev_value": 0.11414647102355957, "name": "array_overlap.MapOverlap.time_map_overlap", "change_rev": [11201, 11203], "idx": 4, "last_rev": 12194, "last_value": 0.11576700210571289, "pretty_name": "array_overlap.MapOverlap.time_map_overlap((50, 512, 512), 'reflect')", "last_err": 0.000679153357452222}, {"prev_value": 0.11518251895904541, "name": "array_overlap.MapOverlap.time_map_overlap", "change_rev": [11151, 11153], "idx": 5, "last_rev": 12194, "last_value": 0.1168980598449707, "pretty_name": "array_overlap.MapOverlap.time_map_overlap((50, 512, 512), 'periodic')", "last_err": 0.0007848237591011895}, {"prev_value": 0.11413097381591797, "name": "array_overlap.MapOverlap.time_map_overlap", "change_rev": [11149, 11151], "idx": 6, "last_rev": 12194, "last_value": 0.11554396152496338, "pretty_name": "array_overlap.MapOverlap.time_map_overlap((50, 512, 512), 'nearest')", "last_err": 0.0006543871223078778}, {"prev_value": 0.07690048217773438, "name": "array_overlap.MapOverlap.time_map_overlap", "change_rev": [10406, 10410], "idx": 7, "last_rev": 12194, "last_value": 0.03271186351776123, "pretty_name": "array_overlap.MapOverlap.time_map_overlap((50, 512, 512), 'none')", "last_err": 0.0004813000776799569}, {"prev_value": null, "name": "dataframe.MemoryDataFrame.time_boolean_indexing", "change_rev": null, "idx": null, "last_rev": 12194, "last_value": 0.09986495971679688, "pretty_name": "dataframe.MemoryDataFrame.time_boolean_indexing", "last_err": 0.01039901874010681}, {"prev_value": 0.049837708473205566, "name": "dataframe.MemoryDataFrame.time_count_values", "change_rev": [9629, 9634], "idx": null, "last_rev": 12194, "last_value": 0.04757046699523926, "pretty_name": "dataframe.MemoryDataFrame.time_count_values", "last_err": 0.0011546790242477148}, {"prev_value": null, "name": "dataframe.MemoryDataFrame.time_groupby", "change_rev": null, "idx": null, "last_rev": 12194, "last_value": 0.20449190139770507, "pretty_name": "dataframe.MemoryDataFrame.time_groupby", "last_err": 0.007969127253382299}, {"prev_value": 0.18377399444580078, "name": "dataframe.MemoryDataFrame.time_reduction", "change_rev": [null, 10503], "idx": null, "last_rev": 12194, "last_value": 0.18652713298797607, "pretty_name": "dataframe.MemoryDataFrame.time_reduction", "last_err": 0.005164129429813961}, {"prev_value": null, "name": "dataframe.MemoryDataFrame.time_scalar_comparison", "change_rev": null, "idx": null, "last_rev": 12194, "last_value": 0.03562074899673462, "pretty_name": "dataframe.MemoryDataFrame.time_scalar_comparison", "last_err": 0.004350360173838746}, {"prev_value": 0.23639202117919922, "name": "dataframe.MemoryDataFrame.time_set_index", "change_rev": [11144, 11149], "idx": null, "last_rev": 12194, "last_value": 0.254457950592041, "pretty_name": "dataframe.MemoryDataFrame.time_set_index", "last_err": 0.008609044471242555}, {"prev_value": null, "name": "io.CSV.time_read_csv", "change_rev": null, "idx": 0, "last_rev": null, "last_value": null, "pretty_name": "io.CSV.time_read_csv(<function get_sync at 0x7f805e4376e0>)", "last_err": null}, {"prev_value": null, "name": "io.CSV.time_read_csv", "change_rev": null, "idx": 1, "last_rev": null, "last_value": null, "pretty_name": "io.CSV.time_read_csv(<function get at 0x7f805d350aa0>)", "last_err": null}, {"prev_value": null, "name": "io.CSV.time_read_csv", "change_rev": null, "idx": 2, "last_rev": null, "last_value": null, "pretty_name": "io.CSV.time_read_csv(<function get at 0x7f805dd40488>)", "last_err": null}, {"prev_value": null, "name": "io.CSV.time_read_csv_meta", "change_rev": null, "idx": 0, "last_rev": null, "last_value": null, "pretty_name": "io.CSV.time_read_csv_meta(<function get_sync at 0x7f805e4376e0>)", "last_err": null}, {"prev_value": null, "name": "io.CSV.time_read_csv_meta", "change_rev": null, "idx": 1, "last_rev": null, "last_value": null, "pretty_name": "io.CSV.time_read_csv_meta(<function get at 0x7f805d350aa0>)", "last_err": null}, {"prev_value": null, "name": "io.CSV.time_read_csv_meta", "change_rev": null, "idx": 2, "last_rev": null, "last_value": null, "pretty_name": "io.CSV.time_read_csv_meta(<function get at 0x7f805dd40488>)", "last_err": null}, {"prev_value": null, "name": "io.HDF5.time_read_hdf5", "change_rev": null, "idx": 0, "last_rev": null, "last_value": null, "pretty_name": "io.HDF5.time_read_hdf5(<function get_sync at 0x7f805e4376e0>)", "last_err": null}, {"prev_value": null, "name": "io.HDF5.time_read_hdf5", "change_rev": null, "idx": 1, "last_rev": null, "last_value": null, "pretty_name": "io.HDF5.time_read_hdf5(<function get at 0x7f805d350aa0>)", "last_err": null}, {"prev_value": null, "name": "io.HDF5.time_read_hdf5", "change_rev": null, "idx": 2, "last_rev": null, "last_value": null, "pretty_name": "io.HDF5.time_read_hdf5(<function get at 0x7f805dd40488>)", "last_err": null}, {"prev_value": null, "name": "io.HDF5.time_read_hdf5_meta", "change_rev": null, "idx": 0, "last_rev": null, "last_value": null, "pretty_name": "io.HDF5.time_read_hdf5_meta(<function get_sync at 0x7f805e4376e0>)", "last_err": null}, {"prev_value": null, "name": "io.HDF5.time_read_hdf5_meta", "change_rev": null, "idx": 1, "last_rev": null, "last_value": null, "pretty_name": "io.HDF5.time_read_hdf5_meta(<function get at 0x7f805d350aa0>)", "last_err": null}, {"prev_value": null, "name": "io.HDF5.time_read_hdf5_meta", "change_rev": null, "idx": 2, "last_rev": null, "last_value": null, "pretty_name": "io.HDF5.time_read_hdf5_meta(<function get at 0x7f805dd40488>)", "last_err": null}]