[{"pretty_name": "array.FancyIndexing.time_fancy", "change_rev": [null, 9877], "prev_value": 0.04376712813973427, "last_value": 0.03710094769485295, "idx": null, "name": "array.FancyIndexing.time_fancy", "last_err": 0.000306641387746125, "last_rev": 11500}, {"pretty_name": "array.Rechunk.time_rechunk", "change_rev": [null, 9391], "prev_value": 0.04204745115894897, "last_value": 0.0379575608142962, "idx": null, "name": "array.Rechunk.time_rechunk", "last_err": 0.0005830857008634257, "last_rev": 11500}, {"pretty_name": "array.Rechunk.time_rechunk_meta", "change_rev": null, "prev_value": null, "last_value": 0.010607093386352063, "idx": null, "name": "array.Rechunk.time_rechunk_meta", "last_err": 0.0011458293673895995, "last_rev": 11500}, {"pretty_name": "array.Slicing.time_slice_int_head", "change_rev": [11470, 11484], "prev_value": 0.018766342972715695, "last_value": 0.020974322455003858, "idx": null, "name": "array.Slicing.time_slice_int_head", "last_err": 6.248920963427708e-05, "last_rev": 11500}, {"pretty_name": "array.Slicing.time_slice_int_tail", "change_rev": null, "prev_value": null, "last_value": 0.018736981476346653, "idx": null, "name": "array.Slicing.time_slice_int_tail", "last_err": 0.0003617073099365657, "last_rev": 11500}, {"pretty_name": "array.Slicing.time_slice_slice_head", "change_rev": null, "prev_value": null, "last_value": 0.037749801335545875, "idx": null, "name": "array.Slicing.time_slice_slice_head", "last_err": 0.0008542537148659917, "last_rev": 11500}, {"pretty_name": "array.Slicing.time_slice_slice_tail", "change_rev": null, "prev_value": null, "last_value": 0.037816107350712024, "idx": null, "name": "array.Slicing.time_slice_slice_tail", "last_err": 0.000796309232146934, "last_rev": 11500}, {"pretty_name": "array.TestSubs.time_subs", "change_rev": [10136, 10158], "prev_value": 0.06612425483763218, "last_value": 0.0641495130257681, "idx": null, "name": "array.TestSubs.time_subs", "last_err": 0.0005267190273100133, "last_rev": 11500}, {"pretty_name": "array.Tokenize.time_tokenize_large", "change_rev": [7006, 7015], "prev_value": 0.0007433866533785801, "last_value": 0.0007999267240916602, "idx": null, "name": "array.Tokenize.time_tokenize_large", "last_err": 6.618748594790483e-06, "last_rev": 11500}, {"pretty_name": "array_overlap.MapOverlap.time_map_overlap((100, 100, 100), 'reflect')", "change_rev": [11196, 11200], "prev_value": 0.08122872351668775, "last_value": 0.08313094405457377, "idx": 0, "name": "array_overlap.MapOverlap.time_map_overlap", "last_err": 0.0009168598055111465, "last_rev": 11500}, {"pretty_name": "array_overlap.MapOverlap.time_map_overlap((100, 100, 100), 'periodic')", "change_rev": [11366, 11369], "prev_value": 0.08109229989349842, "last_value": 0.0842960155569017, "idx": 1, "name": "array_overlap.MapOverlap.time_map_overlap", "last_err": 0.0008388485127618686, "last_rev": 11500}, {"pretty_name": "array_overlap.MapOverlap.time_map_overlap((100, 100, 100), 'nearest')", "change_rev": [11200, 11202], "prev_value": 0.08144475350854918, "last_value": 0.08328918449115008, "idx": 2, "name": "array_overlap.MapOverlap.time_map_overlap", "last_err": 0.001135788523011483, "last_rev": 11500}, {"pretty_name": "array_overlap.MapOverlap.time_map_overlap((100, 100, 100), 'none')", "change_rev": [10403, 10407], "prev_value": 0.04104918451048434, "last_value": 0.022350854007527232, "idx": 3, "name": "array_overlap.MapOverlap.time_map_overlap", "last_err": 0.0016771372506975963, "last_rev": 11500}, {"pretty_name": "array_overlap.MapOverlap.time_map_overlap((50, 512, 512), 'reflect')", "change_rev": [null, 11310], "prev_value": 0.08753847150364891, "last_value": 0.08961238648043945, "idx": 4, "name": "array_overlap.MapOverlap.time_map_overlap", "last_err": 0.0013441328920697317, "last_rev": 11500}, {"pretty_name": "array_overlap.MapOverlap.time_map_overlap((50, 512, 512), 'periodic')", "change_rev": null, "prev_value": null, "last_value": 0.09153979123220779, "idx": 5, "name": "array_overlap.MapOverlap.time_map_overlap", "last_err": 0.001416382308573462, "last_rev": 11500}, {"pretty_name": "array_overlap.MapOverlap.time_map_overlap((50, 512, 512), 'nearest')", "change_rev": null, "prev_value": null, "last_value": 0.08783464482985437, "idx": 6, "name": "array_overlap.MapOverlap.time_map_overlap", "last_err": 0.0013551716810957489, "last_rev": 11500}, {"pretty_name": "array_overlap.MapOverlap.time_map_overlap((50, 512, 512), 'none')", "change_rev": [11200, 11202], "prev_value": 0.027307121010380797, "last_value": 0.02813346401671879, "idx": 7, "name": "array_overlap.MapOverlap.time_map_overlap", "last_err": 0.00036602686006594623, "last_rev": 11500}, {"pretty_name": "dataframe.MemoryDataFrame.time_boolean_indexing", "change_rev": null, "prev_value": null, "last_value": 0.10342949500773102, "idx": null, "name": "dataframe.MemoryDataFrame.time_boolean_indexing", "last_err": 0.007909104968910213, "last_rev": 11500}, {"pretty_name": "dataframe.MemoryDataFrame.time_count_values", "change_rev": null, "prev_value": null, "last_value": 0.04505756433354691, "idx": null, "name": "dataframe.MemoryDataFrame.time_count_values", "last_err": 0.0007569729637713378, "last_rev": 11500}, {"pretty_name": "dataframe.MemoryDataFrame.time_groupby", "change_rev": null, "prev_value": null, "last_value": 0.1964212377682667, "idx": null, "name": "dataframe.MemoryDataFrame.time_groupby", "last_err": 0.005105902588547738, "last_rev": 11500}, {"pretty_name": "dataframe.MemoryDataFrame.time_reduction", "change_rev": null, "prev_value": null, "last_value": 0.16862452945982415, "idx": null, "name": "dataframe.MemoryDataFrame.time_reduction", "last_err": 0.005046681780752556, "last_rev": 11500}, {"pretty_name": "dataframe.MemoryDataFrame.time_scalar_comparison", "change_rev": [11470, 11484], "prev_value": 0.03445901148370467, "last_value": 0.04610115080140531, "idx": null, "name": "dataframe.MemoryDataFrame.time_scalar_comparison", "last_err": 6.433872422544496e-05, "last_rev": 11500}, {"pretty_name": "dataframe.MemoryDataFrame.time_set_index", "change_rev": [11383, 11388], "prev_value": 0.23416948993690312, "last_value": 0.2628044909797609, "idx": null, "name": "dataframe.MemoryDataFrame.time_set_index", "last_err": 0.004149601825510125, "last_rev": 11500}, {"pretty_name": "io.CSV.time_read_csv(<function get_sync at 0x7f27df3355f0>)", "change_rev": null, "prev_value": null, "last_value": null, "idx": 0, "name": "io.CSV.time_read_csv", "last_err": null, "last_rev": null}, {"pretty_name": "io.CSV.time_read_csv(<function get at 0x7f27de24e9b0>)", "change_rev": null, "prev_value": null, "last_value": null, "idx": 1, "name": "io.CSV.time_read_csv", "last_err": null, "last_rev": null}, {"pretty_name": "io.CSV.time_read_csv(<function get at 0x7f27dec3e398>)", "change_rev": null, "prev_value": null, "last_value": null, "idx": 2, "name": "io.CSV.time_read_csv", "last_err": null, "last_rev": null}, {"pretty_name": "io.CSV.time_read_csv_meta(<function get_sync at 0x7f27df3355f0>)", "change_rev": [null, 11500], "prev_value": 0.024507530266419053, "last_value": 0.02458311547525227, "idx": 0, "name": "io.CSV.time_read_csv_meta", "last_err": 0.0, "last_rev": 11500}, {"pretty_name": "io.CSV.time_read_csv_meta(<function get at 0x7f27de24e9b0>)", "change_rev": [null, 11500], "prev_value": 0.02454935945570469, "last_value": 0.02475729095749557, "idx": 1, "name": "io.CSV.time_read_csv_meta", "last_err": 0.0, "last_rev": 11500}, {"pretty_name": "io.CSV.time_read_csv_meta(<function get at 0x7f27dec3e398>)", "change_rev": [null, 11500], "prev_value": 0.024572865571826696, "last_value": 0.024757246021181345, "idx": 2, "name": "io.CSV.time_read_csv_meta", "last_err": 0.0, "last_rev": 11500}, {"pretty_name": "io.HDF5.time_read_hdf5(<function get_sync at 0x7f27df3355f0>)", "change_rev": null, "prev_value": null, "last_value": null, "idx": 0, "name": "io.HDF5.time_read_hdf5", "last_err": null, "last_rev": null}, {"pretty_name": "io.HDF5.time_read_hdf5(<function get at 0x7f27de24e9b0>)", "change_rev": null, "prev_value": null, "last_value": null, "idx": 1, "name": "io.HDF5.time_read_hdf5", "last_err": null, "last_rev": null}, {"pretty_name": "io.HDF5.time_read_hdf5(<function get at 0x7f27dec3e398>)", "change_rev": null, "prev_value": null, "last_value": null, "idx": 2, "name": "io.HDF5.time_read_hdf5", "last_err": null, "last_rev": null}, {"pretty_name": "io.HDF5.time_read_hdf5_meta(<function get_sync at 0x7f27df3355f0>)", "change_rev": null, "prev_value": null, "last_value": 0.21320297103375196, "idx": 0, "name": "io.HDF5.time_read_hdf5_meta", "last_err": 4.3334351097159465e-05, "last_rev": 11500}, {"pretty_name": "io.HDF5.time_read_hdf5_meta(<function get at 0x7f27de24e9b0>)", "change_rev": null, "prev_value": null, "last_value": null, "idx": 1, "name": "io.HDF5.time_read_hdf5_meta", "last_err": null, "last_rev": null}, {"pretty_name": "io.HDF5.time_read_hdf5_meta(<function get at 0x7f27dec3e398>)", "change_rev": [null, 11500], "prev_value": 0.21342263906262815, "last_value": 0.21291909250430763, "idx": 2, "name": "io.HDF5.time_read_hdf5_meta", "last_err": 0.0, "last_rev": 11500}]